Workbook

Sheet Financial Projections
H1: Page 13 | J1: A. STATEMENT OF REVENUES AND EXPENSES
J2: Current Tax Year | K2: Proposed | L2: Proposed | M2: Proposed | N2: Actuals
J3: 45658 | K3: Present to | L3: 46023 | M3: 46388 | N3: 45292
J4: To present | K4: 46022 | L4: 46387 | M4: 46752 | N4: 45657
H5: Revenue
B6: Revenue for 1023 online | G6: 40000 | H6: Direct Contributions Revenue
A7: 1 | B7: =J7+J8 -> 20000 | C7: =#REF!+#REF! -> #REF! | D7: =K7+K8 -> 380000 | E7: =L7+L8 -> 750000 | F7: 1 | G7: 40100 | H7: Individual/Small business contributions | J7: 20000 | K7: 0 | L7: 50000 | M7: 100000
A8: 2 | B8: =J11 -> 0 | C8: =#REF! -> #REF! | D8: =K11 -> 0 | E8: =L11 -> 0 | F8: 1 | G8: 40200 | H8: Corporate Contributions | J8: 0 | K8: 380000 | L8: 700000 | M8: 1000000
A9: 3 | B9: =J13 -> 0 | C9: =#REF! -> #REF! | D9: =K13 -> 2650 | E9: =L13 -> 9800 | H9: Subtotal Line 1 | J9: =SUM(J7:J8) -> 20000 | K9: =SUM(K7:K8) -> 380000 | L9: =SUM(L7:L8) -> 750000 | M9: =SUM(M7:M8) -> 1100000
G10: 46000 | H10: Membership Dues | J10: 0 | K10: 0 | L10: 0 | M10: 0
F11: 2 | G11: 46100 | H11: Membership Dues | I11: 2 | J11: 0 | K11: 0 | L11: 0 | M11: 0
G12: 48000 | H12: Investment Revenue
F13: 3 | G13: 48100 | H13: Interest-- Savings/Short-term Investments | I13: 3 | J13: 0 | K13: 2650 | L13: 9800 | M13: 14700
F14: 4 | G14: 49500 | H14: Unrelated Business Income | I14: 4 | J14: 0 | K14: 0 | L14: 0 | M14: 0
A15: 4 | B15: =J14 -> 0 | C15: =#REF! -> #REF! | D15: =K14 -> 0 | E15: =L14 -> 0 | G15: 41000 | H15: Donated Goods & Services Revenue | I15: 7
A16: 9 | B16: =J18+J19+J20+J21+J22+J25+J26+J27+J28+J29+J32+J33 -> 0 | C16: =#REF!+#REF!+#REF!+#REF!+#REF!+#REF!+#REF!+#REF!+#REF!+#REF!+#REF!+#REF! -> #REF! | D16: =K18+K19+K20+K21+K22+K25+K26+K27+K28+K29+K32+K33 -> 0 | E16: =L18+L19+L20+L21+L22+L25+L26+L27+L28+L29+L32+L33 -> 125000 | F16: 7 | G16: 41100 | H16: Gifts In-Kind | J16: 0 | K16: 0 | L16: 0 | M16: 0
F17: 9 | G17: 45000 | H17: Program Service Revenues
G18: 45100 | H18: Program #1 Revenue (Sway for students and general public) | J18: 0 | K18: 0 | L18: 100000 | M18: 350000
G19: 45200 | H19: Program #2 Revenue (faculty training workshops) | J19: 0 | K19: 0 | L19: 25000 | M19: 50000
G20: 45300 | H20: Program #3 Revenue (empirical research studies) | J20: 0 | K20: 0 | L20: 0 | M20: 0
G21: 45400 | H21: Program #4 Revenue | J21: 0 | K21: 0 | L21: 0 | M21: 0
G22: 45500 | H22: Program #5 Revenue | J22: 0 | K22: 0 | L22: 0 | M22: 0
G24: 47000 | H24: Fundraising Event Revenues | J24: 0 | K24: 0 | L24: 0 | M24: 0
F25: 9 | G25: 47100 | H25: Fundraising Event #1 Gross Revenue | J25: 0 | K25: 0 | L25: 0 | M25: 0
F26: 9 | G26: 47200 | H26: Fundraising Event #2 Gross Revenue | J26: 0 | K26: 0 | L26: 0 | M26: 0
F27: 9 | G27: 47300 | H27: Fundraising Event #3 Gross Revenue | J27: 0 | K27: 0 | L27: 0 | M27: 0
F28: 9 | G28: 47400 | H28: Fundraising Event #4 Gross Revenue | J28: 0 | K28: 0 | L28: 0 | M28: 0
F29: 9 | G29: 47500 | H29: Fundraising Event #5 Gross Revenue | J29: 0 | K29: 0 | L29: 0 | M29: 0
G31: 49000 | H31: Other Revenues | J31: 0 | K31: 0 | L31: 0 | M31: 0
F32: 9 | G32: 49100 | H32: Non-Inventory Sales-- Gross | J32: 0 | K32: 0 | L32: 0 | M32: 0
F33: 9 | G33: 49200 | H33: Inventory Sales-- Gross | J33: 0 | K33: 0 | L33: 0 | M33: 0
H34: Subtotal Line 9 | J34: =SUM(J18:J33) -> 0 | K34: =SUM(K18:K33) -> 0 | L34: =SUM(L18:L33) -> 125000 | M34: =SUM(M18:M33) -> 400000
F35: 13 | H35: Total Income/Revenue | J35: =J34+J16+J14+J13+J11+J9 -> 20000 | K35: =K34+K16+K14+K13+K11+K9 -> 382650 | L35: =L34+L16+L14+L13+L11+L9 -> 884800 | M35: =M34+M16+M14+M13+M11+M9 -> 1514700
B36: Expenses for 1023 online
H37: Expenses
G39: 70000 | H39: Fundraising Expenses
F40: 14 | G40: 71000 | H40: Fundraising Event #1 Cash Prizes | J40: 0 | K40: 0 | L40: 0 | M40: 0
F41: 14 | G41: 71100 | H41: Fundraising Event #1 Noncash prizes | J41: 0 | K41: 0 | L41: 0 | M41: 0
F42: 14 | G42: 71200 | H42: Fundraising Event #1 Rent/Facility Costs | J42: 0 | K42: 0 | L42: 0 | M42: 0
F43: 14 | G43: 71300 | H43: Fundraising Event #1 Food & Beverage | J43: 0 | K43: 0 | L43: 0 | M43: 0
F44: 14 | G44: 71400 | H44: Fundraising Event #1 Entertainment | J44: 0 | K44: 0 | L44: 0 | M44: 0
F45: 14 | G45: 71500 | H45: Fundraising Event #1 Other direct fundraiser costs | J45: 0 | K45: 0 | L45: 0 | M45: 0
F47: 14 | G47: 72000 | H47: Fundraising Event #2 Cash Prizes | J47: 0 | K47: 0 | L47: 0 | M47: 0
F48: 14 | G48: 72100 | H48: Fundraising Event #2 Noncash prizes | J48: 0 | K48: 0 | L48: 0 | M48: 0
F49: 14 | G49: 72200 | H49: Fundraising Event #2 Rent/Facility Costs | J49: 0 | K49: 0 | L49: 0 | M49: 0
F50: 14 | G50: 72300 | H50: Fundraising Event #2 Food & Beverage | J50: 0 | K50: 0 | L50: 0 | M50: 0
F51: 14 | G51: 72400 | H51: Fundraising Event #2 Entertainment | J51: 0 | K51: 0 | L51: 0 | M51: 0
F52: 14 | G52: 72500 | H52: Fundraising Event #2 Other direct fundraiser costs | J52: 0 | K52: 0 | L52: 0 | M52: 0
... F59: 14 | G59: 73500 | H59: Fundraising Event #3 Other direct fundraiser costs | J59: 0 | K59: 0 | L59: 0 | M59: 0
H60: Subtotal Line 14 | J60: =SUM(J40:J59) -> 0 | K60: =SUM(K40:K59) -> 0 | L60: =SUM(L40:L59) -> 0 | M60: =SUM(M40:M59) -> 0
A61: 14 | B61: =SUM(#REF!) -> #REF! | C61: =SUM(#REF!) -> #REF! | D61: =SUM(#REF!) -> #REF! | E61: =SUM(#REF!) -> #REF! | G61: 50000 | H61: Grants, Awards & Direct Assistance | J61: 0 | K61: 0 | L61: 0 | M61: 0
A62: 15 | B62: =J62:J66 -> 0 | C62: =#REF! -> #REF! | D62: =K62:K66 -> 0 | E62: =L62:L66 -> 0 | F62: 15 | G62: 50100 | H62: Grants to other NPOs (in US) | J62: 0 | K62: 0 | L62: 0 | M62: 0
A63: 16 | B63: =J68 -> 0 | C63: =#REF! -> #REF! | D63: =K68 -> 0 | E63: =L68 -> 0 | F63: 15 | G63: 50200 | H63: Grants to other NPOs (outside US) | J63: 0 | K63: 0 | L63: 0 | M63: 0
A64: 17 | B64: =J71+J72 -> 0 | C64: =#REF!+#REF! -> #REF! | D64: =K71+K72 -> 15000 | E64: =L71+L72 -> 471500 | F64: 15 | G64: 50300 | H64: Grants & Awards to Individuals (in US) | J64: 0 | K64: 0 | L64: 0 | M64: 0
A65: 18 | B65: =J74+J75 -> 0 | C65: =#REF!+#REF! -> #REF! | D65: =K74+K75 -> 0 | E65: =L74+L75 -> 0 | F65: 15 | G65: 50400 | H65: Grants & Awards to Individuals (outside US) | J65: 0 | K65: 0 | L65: 0 | M65: 0
A66: 20 | B66: =J78+J79+J80+J81+J82+J83 -> 0 | C66: =#REF!+#REF!+#REF!+#REF!+#REF!+#REF! -> #REF! | D66: =K78+K79+K80+K81+K82+K83 -> 0 | E66: =L78+L79+L80+L81+L82+L83 -> 0 | F66: 15 | G66: 50500 | H66: Benevolent Assistance to Individuals | J66: 0 | K66: 0 | L66: 0 | M66: 0
H67: Subtotal Line 15 | J67: =SUM(J62:J66) -> 0 | K67: =SUM(K62:K66) -> 0 | L67: =SUM(L62:L66) -> 0 | M67: =SUM(M62:M66) -> 0
F68: 16 | G68: 50600 | H68: Benefits Paid to/for Members | J68: 0 | K68: 0 | L68: 0 | M68: 0
A69: 22 | B69: =J86+J87+J88+J89+J90 -> 46336 | C69: =#REF!+#REF!+#REF!+#REF!+#REF! -> #REF! | D69: =K86+K87+K88+K89+K90 -> 111375 | E69: =L86+L87+L88+L89+L90 -> 298000 | H69: Subtotal Line 16 | J69: =J68 -> 0 | K69: =K68 -> 0 | L69: =L68 -> 0 | M69: =M68 -> 0
A70: 23 | B70: =J135+J136+J121+J92+J93+J95+J96+J97+J98+J99+J100+J101+J102+J103+J105+J106+J108+J107+J110+J111+J112+J114+J115+J116+J117+J118+J119+J120+J122+J123+J125+#REF!+J126+J127+J129+J130+J131+J132+J133+J134 -> #REF! | C70: =#REF!+#REF!+#REF!+#REF!+#REF!+#REF!+#REF!+#REF!+#REF!+#REF!+#REF!+#REF!+#REF!+#REF!+#REF!+#REF!+#REF!+#REF!+#REF!+#REF!+#REF!+#REF!+#REF!+#REF!+#REF!+#REF!+#REF!+#REF!+#REF!+#REF!+#REF!+#REF!+#REF!+#REF!+#REF!+#REF!+#REF!+#REF!+#REF!+#REF! -> #REF! | D70: =K135+K136+K121+K92+K93+K95+K96+K97+K98+K99+K100+K101+K102+K103+K105+K106+K108+K107+K110+K111+K112+K114+K115+K116+K117+K118+K119+K120+K122+K123+K125+#REF!+K126+K127+K129+K130+K131+K132+K133+K134 -> #REF! | E70: =L135+L136+L121+L92+L93+L95+L96+L97+L98+L99+L100+L101+L102+L103+L105+L106+L108+L107+L110+L111+L112+L114+L115+L116+L117+L118+L119+L120+L122+L123+L125+#REF!+L126+L127+L129+L130+L131+L132+L133+L134 -> #REF! | G70: 51000 | H70: Salaries & Related Expenses
F71: 17 | G71: 51100 | H71: Officers, Directors/Trustees, Key Employees Salaries | J71: 0 | K71: 15000 | L71: 410000 | M71: 560000
F72: 17 | G72: 51400 | H72: Employee Benefits (not pension)--O, D/T, KE | J72: 0 | K72: 0 | L72: 61500 | M72: 84000
H73: Subtotal Line 17 | J73: =SUM(J71:J72) -> 0
F74: 18 | G74: 51200 | H74: Salaries & Wages- Other | J74: 0 | K74: 0 | L74: 0 | M74: 0
F75: 18 | G75: 51450 | H75: Employee Benefits (not pension)-- Other | J75: 0 | K75: 0 | L75: 0 | M75: 0
H76: Subtotal Line 18 | J76: =SUM(J74:J75) -> 0 | K76: =SUM(K74:K75) -> 0 | L76: =SUM(L74:L75) -> 0 | M76: =SUM(M74:M75) -> 0
G77: 54000 | H77: Occupancy | J77: 0 | K77: 0 | L77: 0 | M77: 0
F78: 20 | G78: 54100 | H78: Rent/Mortgage/Lease | J78: 0 | K78: 0 | L78: 0 | M78: 0
F79: 20 | G79: 54200 | H79: Utilities | J79: 0 | K79: 0 | L79: 0 | M79: 0
F80: 20 | G80: 54300 | H80: Insurance | J80: 0 | K80: 0 | L80: 0 | M80: 0
F81: 20 | G81: 54400 | H81: Property Taxes | J81: 0 | K81: 0 | L81: 0 | M81: 0
F82: 20 | G82: 54500 | H82: Mortgage Interest | J82: 0 | K82: 0 | L82: 0 | M82: 0
F83: 20 | G83: 54600 | H83: Building Maintenance | J83: 0 | K83: 0 | L83: 0 | M83: 0
H84: Subtotal Line 20 | J84: =SUM(J78:J83) -> 0 | K84: =SUM(K78:K83) -> 0 | L84: =SUM(L78:L83) -> 0 | M84: =SUM(M78:M83) -> 0
G85: 52000 | H85: Contract Services Expenses
F86: 22 | G86: 52200 | H86: Accounting Fees | J86: 2534 | K86: 5000 | L86: 15000 | M86: 20000
F87: 22 | G87: 52400 | H87: Professional Fees- Other (includes FG fees) | J87: 42702 | K87: 106375 | L87: 263000 | M87: 405000
F88: 22 | G88: 52500 | H88: Temporary Help- Contract Labor | J88: 1100 | K88: 0 | L88: 20000 | M88: 30000
F89: 22 | G89: 52600 | H89: Management Fees | J89: 0 | K89: 0 | L89: 0 | M89: 0
F90: 22 | G90: 52800 | H90: Investment Management Fees | J90: 0 | K90: 0 | L90: 0 | M90: 0
H91: Subtotal Line 22 | J91: =SUM(J86:J90) -> 46336 | K91: =SUM(K86:K90) -> 111375 | L91: =SUM(L86:L90) -> 298000 | M91: =SUM(M86:M90) -> 455000
F92: 23 | G92: 52300 | H92: Legal Fees | J92: 0 | K92: 3000 | L92: 2500 | M92: 10000
F93: 23 | G93: 52700 | H93: Lobbying Fees | J93: 0 | K93: 0 | L93: 0 | M93: 0
G94: 53000 | H94: Office Expenses
F95: 23 | G95: 53100 | H95: Supplies | J95: 80 | K95: 280 | L95: 1000 | M95: 5000
F96: 23 | G96: 53200 | H96: Telephone & Telecommunications | J96: 0 | K96: 0 | L96: 1000 | M96: 1000
F97: 23 | G97: 53300 | H97: Postage & Shipping | J97: 0 | K97: 30 | L97: 50 | M97: 50
F98: 23 | G98: 53400 | H98: Printing & Copying | J98: 0 | K98: 50 | L98: 100 | M98: 150
F99: 23 | G99: 53500 | H99: Books, Subscriptions, References | J99: 0 | K99: 0 | L99: 0 | M99: 0
F100: 23 | G100: 53600 | H100: In-house Publications | J100: 0 | K100: 0 | L100: 0 | M100: 10000
F101: 23 | G101: 53700 | H101: Equipment Rental & Maintenance | J101: 0 | K101: 0 | L101: 0 | M101: 0
F102: 23 | G102: 53800 | H102: Licenses, Fees & Dues (includes IRS & State fees) | J102: 0 | K102: 725 | L102: 300 | M102: 350
F103: 23 | G103: 53900 | H103: Bank Service Charges | J103: 0 | K103: 0 | L103: 0 | M103: 0
G104: 55000 | H104: Travel Expenses
F105: 23 | G105: 55100 | H105: Transportation, Mileage | J105: 875 | K105: 1000 | L105: 9000 | M105: 11000
F106: 23 | G106: 55200 | H106: Lodging | J106: 400 | K106: 500 | L106: 7000 | M106: 8000
F107: 23 | G107: 55300 | H107: Meals, Per diem | J107: 0 | K107: 0 | L107: 5600 | M107: 6000
F108: 23 | G108: 55400 | H108: Company Vehicles Expenses | J108: 0 | K108: 0 | L108: 0 | M108: 0
G109: 56000 | H109: Conferences, Conventions & Meetings
F110: 23 | G110: 56100 | H110: Venue Rental & Related Expenses | J110: 0 | K110: 0 | L110: 6500 | M110: 6500
...

Sheet Salary Breakdown
A1: Salary Breakdown - totals should transfer to Chart of Accounts lines 51100 & 51200 respectively | C1: Current Tax Year 1/1/2025 - Present | D1: Proposed Present - 12/31/2025 | E1: Proposed 1/1/2026 - 12/31/2026 | F1: Proposed 1/1/2027 - 12/31/2027 | G1: Actuals 1/1/2024 - 12/31/2024
A4: Line 17 | B4: Officers, Directors/Trustees, Key Employees Salaries (51100)
B5: Simon Cullen, President/Scientist | C5: 0 | D5: 0 | E5: 0 | F5: 150000 | G5: 0
B6: Nicholas DiBella, Treasurer/Secretary/Scientist | C6: 0 | D6: 15000 | E6: 110000 | F6: 110000
B7: Director of Technical Programs
B8: Research Scientist | C8: 0 | D8: 0 | E8: 100000 | F8: 100000
B9: Research Scientist | C9: 0 | D9: 0 | E9: 100000 | F9: 100000
A11: 51100 | B11: Total carries to Line 51100 of Chart of Accounts | C11: =SUM(C5:C10) -> 0 | D11: =SUM(D5:D10) -> 15000 | E11: =SUM(E5:E10) -> 310000 | F11: =SUM(F5:F10) -> 460000 | G11: =SUM(G5:G10) -> 0
A13: Line 18 | B13: Salaries & Wages- Other (51200)
B15: Job Title /Name of Person Hired, (if known)
B16: Job Title /Name of Person Hired, (if known)
B17: Job Title /Name of Person Hired, (if known)
A19: 51200 | B19: Total carries to Line 51200 of Chart of Accounts | C19: =SUM(C14:C18) -> 0 | D19: =SUM(D14:D18) -> 0 | E19: =SUM(E14:E18) -> 0 | F19: =SUM(F14:F18) -> 0 | G19: =SUM(G14:G18) -> 0
D147: =SUM(D43:D146) -> 0 | E147: =SUM(E43:E146) -> 0 | F147: =SUM(F43:F146) -> 0 | G147: =SUM(G43:G146) -> 0

Sheet Financial Actuals
H1: Page 13 | J1: A. STATEMENT OF REVENUES AND EXPENSES
J2: Actuals | K2: Actuals | L2: Actuals | M2: Actuals
J3: 43831 | K3: 44197 | L3: 44562 | M3: 44927
J4: 44196 | K4: 44561 | L4: 44926 | M4: 45291
H5: Revenue
B6: Revenue for 1023 online | G6: 40000 | H6: Direct Contributions Revenue
A7: 1 | B7: =J7+J8 -> 0 | C7: =#REF!+#REF! -> #REF! | D7: =K7+K8 -> 0 | E7: =L7+L8 -> 0 | F7: 1 | G7: 40100 | H7: Individual/Small business contributions
A8: 2 | B8: =J11 | C8: =#REF! -> #REF! | D8: =K11 | E8: =L11 | F8: 1 | G8: 40200 | H8: Corporate Contributions
A9: 3 | B9: =J13 | C9: =#REF! -> #REF! | D9: =K13 | E9: =L13 | H9: Subtotal Line 1 | J9: =SUM(J7:J8) -> 0 | K9: =SUM(K7:K8) -> 0 | L9: =SUM(L7:L8) -> 0 | M9: =SUM(M7:M8) -> 0
G10: 46000 | H10: Membership Dues
F11: 2 | G11: 46100 | H11: Membership Dues
G12: 48000 | H12: Investment Revenue
F13: 3 | G13: 48100 | H13: Interest-- Savings/Short-term Investments
F14: 4 | G14: 49500 | H14: Unrelated Business Income
A15: 4 | B15: =J14 | C15: =#REF! -> #REF! | D15: =K14 | E15: =L14 | G15: 41000 | H15: Donated Goods & Services Revenue
A16: 9 | B16: =J18+J19+J20+J21+J22+J25+J26+J27+J28+J29+J32+J33 -> 0 | C16: =#REF!+#REF!+#REF!+#REF!+#REF!+#REF!+#REF!+#REF!+#REF!+#REF!+#REF!+#REF! -> #REF! | D16: =K18+K19+K20+K21+K22+K25+K26+K27+K28+K29+K32+K33 -> 0 | E16: =L18+L19+L20+L21+L22+L25+L26+L27+L28+L29+L32+L33 -> 0 | F16: 7 | G16: 41100 | H16: Gifts In-Kind
F17: 9 | G17: 45000 | H17: Program Service Revenues
G18: 45100 | H18: Program #1 Revenue
G19: 45200 | H19: Program #2 Revenue
G20: 45300 | H20: Program #3 Revenue
G21: 45400 | H21: Program #4 Revenue
G22: 45500 | H22: Program #5 Revenue
G24: 47000 | H24: Fundraising Event Revenues
F25: 9 | G25: 47100 | H25: Fundraising Event #1 Gross Revenue
F26: 9 | G26: 47200 | H26: Fundraising Event #2 Gross Revenue
F27: 9 | G27: 47300 | H27: Fundraising Event #3 Gross Revenue
F28: 9 | G28: 47400 | H28: Fundraising Event #4 Gross Revenue
F29: 9 | G29: 47500 | H29: Fundraising Event #5 Gross Revenue
G31: 49000 | H31: Other Revenues
F32: 9 | G32: 49100 | H32: Non-Inventory Sales-- Gross
F33: 9 | G33: 49200 | H33: Inventory Sales-- Gross
H34: Subtotal Line 9 | J34: =SUM(J18:J33) -> 0 | K34: =SUM(K18:K33) -> 0 | L34: =SUM(L18:L33) -> 0 | M34: =SUM(M18:M33) -> 0
F35: 13 | H35: Total Income/Revenue | J35: =J34+J16+J14+J13+J11+J9 -> 0 | K35: =K34+K16+K14+K13+K11+K9 -> 0 | L35: =L34+L16+L14+L13+L11+L9 -> 0 | M35: =M34+M16+M14+M13+M11+M9 -> 0
B36: Expenses for 1023 online
H37: Expenses
G39: 70000 | H39: Fundraising Expenses
F40: 14 | G40: 71000 | H40: Fundraising Event #1 Cash Prizes
F41: 14 | G41: 71100 | H41: Fundraising Event #1 Noncash prizes
F42: 14 | G42: 71200 | H42: Fundraising Event #1 Rent/Facility Costs
F43: 14 | G43: 71300 | H43: Fundraising Event #1 Food & Beverage
F44: 14 | G44: 71400 | H44: Fundraising Event #1 Entertainment
F45: 14 | G45: 71500 | H45: Fundraising Event #1 Other direct fundraiser costs
F47: 14 | G47: 72000 | H47: Fundraising Event #2 Cash Prizes
F48: 14 | G48: 72100 | H48: Fundraising Event #2 Noncash prizes
F49: 14 | G49: 72200 | H49: Fundraising Event #2 Rent/Facility Costs
F50: 14 | G50: 72300 | H50: Fundraising Event #2 Food & Beverage
F51: 14 | G51: 72400 | H51: Fundraising Event #2 Entertainment
F52: 14 | G52: 72500 | H52: Fundraising Event #2 Other direct fundraiser costs
... F59: 14 | G59: 73500 | H59: Fundraising Event #3 Other direct fundraiser costs
H60: Subtotal Line 14 | J60: =SUM(J40:J59) -> 0 | K60: =SUM(K40:K59) -> 0 | L60: =SUM(L40:L59) -> 0 | M60: =SUM(M40:M59) -> 0
A61: 14 | B61: =SUM(#REF!) -> #REF! | C61: =SUM(#REF!) -> #REF! | D61: =SUM(#REF!) -> #REF! | E61: =SUM(#REF!) -> #REF! | G61: 50000 | H61: Grants, Awards & Direct Assistance
A62: 15 | B62: =J62:J66 | C62: =#REF! -> #REF! | D62: =K62:K66 | E62: =L62:L66 | F62: 15 | G62: 50100 | H62: Grants to other NPOs (in US)
A63: 16 | B63: =J68 | C63: =#REF! -> #REF! | D63: =K68 | E63: =L68 | F63: 15 | G63: 50200 | H63: Grants to other NPOs (outside US)
A64: 17 | B64: =J71+J72 -> 0 | C64: =#REF!+#REF! -> #REF! | D64: =K71+K72 -> 15000 | E64: =L71+L72 -> 310000 | F64: 15 | G64: 50300 | H64: Grants & Awards to Individuals (in US)
A65: 18 | B65: =J74+J75 -> 0 | C65: =#REF!+#REF! -> #REF! | D65: =K74+K75 -> 0 | E65: =L74+L75 -> 0 | F65: 15 | G65: 50400 | H65: Grants & Awards to Individuals (outside US)
A66: 20 | B66: =J78+J79+J80+J81+J82+J83 -> 0 | C66: =#REF!+#REF!+#REF!+#REF!+#REF!+#REF! -> #REF! | D66: =K78+K79+K80+K81+K82+K83 -> 0 | E66: =L78+L79+L80+L81+L82+L83 -> 0 | F66: 15 | G66: 50500 | H66: Benevolent Assistance to Individuals
H67: Subtotal Line 15 | J67: =SUM(J62:J66) -> 0 | K67: =SUM(K62:K66) -> 0 | L67: =SUM(L62:L66) -> 0 | M67: =SUM(M62:M66) -> 0
F68: 16 | G68: 50600 | H68: Benefits Paid to/for Members
A69: 22 | B69: =J86+J87+J88+J89+J90 -> 0 | C69: =#REF!+#REF!+#REF!+#REF!+#REF! -> #REF! | D69: =K86+K87+K88+K89+K90 -> 0 | E69: =L86+L87+L88+L89+L90 -> 0 | H69: Subtotal Line 16 | J69: =J68 | K69: =K68 | L69: =L68 | M69: =M68
A70: 23 | B70: =J135+J136+J121+J92+J93+J95+J96+J97+J98+J99+J100+J101+J102+J103+J105+J106+J108+J107+J110+J111+J112+J114+J115+J116+J117+J118+J119+J120+J122+J123+J125+J126+J127+J128+J129+J130+J131+J132+J133+J134 -> 0 | C70: =#REF!+#REF!+#REF!+#REF!+#REF!+#REF!+#REF!+#REF!+#REF!+#REF!+#REF!+#REF!+#REF!+#REF!+#REF!+#REF!+#REF!+#REF!+#REF!+#REF!+#REF!+#REF!+#REF!+#REF!+#REF!+#REF!+#REF!+#REF!+#REF!+#REF!+#REF!+#REF!+#REF!+#REF!+#REF!+#REF!+#REF!+#REF!+#REF!+#REF! -> #REF! | D70: =K135+K136+K121+K92+K93+K95+K96+K97+K98+K99+K100+K101+K102+K103+K105+K106+K108+K107+K110+K111+K112+K114+K115+K116+K117+K118+K119+K120+K122+K123+K125+K126+K127+K128+K129+K130+K131+K132+K133+K134 -> 0 | E70: =L135+L136+L121+L92+L93+L95+L96+L97+L98+L99+L100+L101+L102+L103+L105+L106+L108+L107+L110+L111+L112+L114+L115+L116+L117+L118+L119+L120+L122+L123+L125+L126+L127+L128+L129+L130+L131+L132+L133+L134 -> 0 | G70: 51000 | H70: Salaries & Related Expenses
F71: 17 | G71: 51100 | H71: Officers, Directors/Trustees, Key Employees Salaries | J71: ='Salary Breakdown'!C11 -> 0 | K71: ='Salary Breakdown'!D11 -> 15000 | L71: ='Salary Breakdown'!E11 -> 310000 | M71: ='Salary Breakdown'!F11 -> 460000
F72: 17 | G72: 51400 | H72: Employee Benefits (not pension)--O, D/T, KE
H73: Subtotal Line 17 | J73: =SUM(J71:J72) -> 0 | K73: =SUM(K71:K72) -> 15000 | L73: =SUM(L71:L72) -> 310000 | M73: =SUM(M71:M72) -> 460000
F74: 18 | G74: 51200 | H74: Salaries & Wages- Other | J74: ='Salary Breakdown'!C19 -> 0 | K74: ='Salary Breakdown'!D19 -> 0 | L74: ='Salary Breakdown'!E19 -> 0 | M74: ='Salary Breakdown'!F19 -> 0
F75: 18 | G75: 51450 | H75: Employee Benefits (not pension)-- Other
H76: Subtotal Line 18 | J76: =SUM(J74:J75) -> 0 | K76: =SUM(K74:K75) -> 0 | L76: =SUM(L74:L75) -> 0 | M76: =SUM(M74:M75) -> 0
G77: 54000 | H77: Occupancy
F78: 20 | G78: 54100 | H78: Rent/Mortgage/Lease
F79: 20 | G79: 54200 | H79: Utilities
F80: 20 | G80: 54300 | H80: Insurance
F81: 20 | G81: 54400 | H81: Property Taxes
F82: 20 | G82: 54500 | H82: Mortgage Interest
F83: 20 | G83: 54600 | H83: Building Maintenance
H84: Subtotal Line 20 | J84: =SUM(J78:J83) -> 0 | K84: =SUM(K78:K83) -> 0 | L84: =SUM(L78:L83) -> 0 | M84: =SUM(M78:M83) -> 0
G85: 52000 | H85: Contract Services Expenses
F86: 22 | G86: 52200 | H86: Accounting Fees
F87: 22 | G87: 52400 | H87: Professional Fees- Other
F88: 22 | G88: 52500 | H88: Temporary Help- Contract Labor
F89: 22 | G89: 52600 | H89: Management Fees
F90: 22 | G90: 52800 | H90: Investment Management Fees
H91: Subtotal Line 22 | J91: =SUM(J86:J90) -> 0 | K91: =SUM(K86:K90) -> 0 | L91: =SUM(L86:L90) -> 0 | M91: =SUM(M86:M90) -> 0
F92: 23 | G92: 52300 | H92: Legal Fees
F93: 23 | G93: 52700 | H93: Lobbying Fees
G94: 53000 | H94: Office Expenses
F95: 23 | G95: 53100 | H95: Supplies
F96: 23 | G96: 53200 | H96: Telephone & Telecommunications
F97: 23 | G97: 53300 | H97: Postage & Shipping
F98: 23 | G98: 53400 | H98: Printing & Copying
F99: 23 | G99: 53500 | H99: Books, Subscriptions, References
F100: 23 | G100: 53600 | H100: In-house Publications
F101: 23 | G101: 53700 | H101: Equipment Rental & Maintenance
F102: 23 | G102: 53800 | H102: Licenses, Fees & Dues
F103: 23 | G103: 53900 | H103: Bank Service Charges
G104: 55000 | H104: Travel Expenses
F105: 23 | G105: 55100 | H105: Transportation, Mileage
F106: 23 | G106: 55200 | H106: Lodging
F107: 23 | G107: 55300 | H107: Meals, Per diem
F108: 23 | G108: 55400 | H108: Company Vehicles Expenses
G109: 56000 | H109: Conferences, Conventions & Meetings
F110: 23 | G110: 56100 | H110: Venue Rental & Related Expenses
...

Sheet Program Expense Itemize List
A1: Expense Item | B1: Estimated Cost
